python_cmake_module/_dummy.cpython-311-x86_64-linux-gnu.so
ros_python_cmake_module-0.11.1.data/data/share/ament_index/resource_index/package_run_dependencies/python_cmake_module
ros_python_cmake_module-0.11.1.data/data/share/ament_index/resource_index/packages/python_cmake_module
ros_python_cmake_module-0.11.1.data/data/share/ament_index/resource_index/parent_prefix_path/python_cmake_module
ros_python_cmake_module-0.11.1.data/data/share/python_cmake_module/local_setup.bash
ros_python_cmake_module-0.11.1.data/data/share/python_cmake_module/local_setup.dsv
ros_python_cmake_module-0.11.1.data/data/share/python_cmake_module/local_setup.sh
ros_python_cmake_module-0.11.1.data/data/share/python_cmake_module/local_setup.zsh
ros_python_cmake_module-0.11.1.data/data/share/python_cmake_module/package.dsv
ros_python_cmake_module-0.11.1.data/data/share/python_cmake_module/package.xml
ros_python_cmake_module-0.11.1.data/data/share/python_cmake_module/cmake/python_cmake_module-extras.cmake
ros_python_cmake_module-0.11.1.data/data/share/python_cmake_module/cmake/python_cmake_moduleConfig-version.cmake
ros_python_cmake_module-0.11.1.data/data/share/python_cmake_module/cmake/python_cmake_moduleConfig.cmake
ros_python_cmake_module-0.11.1.data/data/share/python_cmake_module/cmake/Modules/FindPythonExtra.cmake
ros_python_cmake_module-0.11.1.data/data/share/python_cmake_module/environment/ament_prefix_path.dsv
ros_python_cmake_module-0.11.1.data/data/share/python_cmake_module/environment/ament_prefix_path.sh
ros_python_cmake_module-0.11.1.data/data/share/python_cmake_module/environment/path.dsv
ros_python_cmake_module-0.11.1.data/data/share/python_cmake_module/environment/path.sh
ros_python_cmake_module-0.11.1.dist-info/METADATA
ros_python_cmake_module-0.11.1.dist-info/WHEEL
ros_python_cmake_module-0.11.1.dist-info/top_level.txt
ros_python_cmake_module-0.11.1.dist-info/RECORD
ros_python_cmake_module-0.11.1.dist-info/licenses/LICENSE
