Metadata-Version: 2.4
Name: ros-python-cmake-module
Version: 0.11.1
Summary: Wheel for the python_cmake_module (ros-python-cmake-module) ROS 2 package.
License-File: LICENSE
Dynamic: description
Dynamic: description-content-type
Dynamic: license-file
Dynamic: summary
